LICENSE
README.md
setup.cfg
setup.py
bigquery_utils/__init__.py
bigquery_utils/config_util.py
bigquery_utils.egg-info/PKG-INFO
bigquery_utils.egg-info/SOURCES.txt
bigquery_utils.egg-info/dependency_links.txt
bigquery_utils.egg-info/requires.txt
bigquery_utils.egg-info/top_level.txt