Metadata-Version: 2.1
Name: bigquery-utils
Version: 0.0.2
Summary: Utilities for creating, loading and querying bigquery tables.
Home-page: https://github.com/aParthemer/bigquery_utils
Author: Alex Parthemer
Author-email: alexparthemer@gmail.com
License: MIT
Download-URL: https://github.com/aParthemer/bigquery_utils/archive/refs/tags/v0.0.2.tar.gz
Project-URL: Bug Tracker, https://github.com/aParthemer/bigquery_utils/issues
Platform: UNKNOWN
Classifier: Development Status :: 3 - Alpha
License-File: LICENSE
